[
  {
    "title": "Shadow Registeel in Shadow Raids",
    "date": 1751673600000,
    "dateEnd": 1754179200000,
    "raids": [
      {
        "speciesId": "registeel_shadow",
        "kind": "5",
        "shiny": false
      }
    ],
    "rawUrl": "https://leekduck.com/events/shadow-registeel-in-shadow-raids-july-august-2025/"
  },
  {
    "title": "Mega Charizard Y in Mega Raids",
    "date": 1751932800000,
    "dateEnd": 1752451200000,
    "raids": [
      {
        "speciesId": "charizard_mega_x",
        "kind": "mega",
        "shiny": false
      }
    ],
    "rawUrl": "https://leekduck.com/events/mega-charizard-x-in-mega-raids-july-2025/"
  },
  {
    "title": "Solgaleo in 5-star Raid Battles",
    "date": 1751932800000,
    "dateEnd": 1752451200000,
    "raids": [
      {
        "speciesId": "solgaleo",
        "kind": "5",
        "shiny": false
      }
    ],
    "rawUrl": "https://leekduck.com/events/solgaleo-in-5-star-raid-battles-july-2025/"
  },
  {
    "title": "Mega Blastoise in Mega Raids",
    "date": 1752451200000,
    "dateEnd": 1753142400000,
    "raids": [
      {
        "speciesId": "blastoise_mega",
        "kind": "mega",
        "shiny": false
      }
    ],
    "rawUrl": "https://leekduck.com/events/mega-blastoise-in-mega-raids-july-2025/"
  },
  {
    "title": "Terrakion in 5-star Raid Battles",
    "date": 1752451200000,
    "dateEnd": 1753142400000,
    "raids": [
      {
        "speciesId": "terrakion",
        "kind": "5",
        "shiny": false
      }
    ],
    "rawUrl": "https://leekduck.com/events/terrakion-in-5-star-raid-battles-july-2025/"
  },
  {
    "title": "Lunala in 5-star Raid Battles",
    "date": 1753142400000,
    "dateEnd": 1753660800000,
    "raids": [
      {
        "speciesId": "lunala",
        "kind": "5",
        "shiny": false
      }
    ],
    "rawUrl": "https://leekduck.com/events/lunala-in-5-star-raid-battles-july-2025/"
  },
  {
    "title": "Mega Venusaur in Mega Raids",
    "date": 1753142400000,
    "dateEnd": 1753660800000,
    "raids": [
      {
        "speciesId": "venusaur_mega",
        "kind": "mega",
        "shiny": false
      }
    ],
    "rawUrl": "https://leekduck.com/events/mega-venusaur-in-mega-raids-july-2025/"
  },
  {
    "title": "Mega Aerodactyl in Mega Raids",
    "date": 1753660800000,
    "dateEnd": 1754265600000,
    "raids": [
      {
        "speciesId": "aerodactyl_mega",
        "kind": "mega",
        "shiny": false
      }
    ],
    "rawUrl": "https://leekduck.com/events/mega-aerodactyl-in-mega-raids-july-august-2025/"
  },
  {
    "title": "Virizion in 5-star Raid Battles",
    "date": 1753660800000,
    "dateEnd": 1754265600000,
    "raids": [
      {
        "speciesId": "virizion",
        "kind": "5",
        "shiny": false
      }
    ],
    "rawUrl": "https://leekduck.com/events/virizion-in-5-star-raid-battles-july-august-2025/"
  }
]