[
	{
		"title": {
			"en": "Aron Spotlight Hour",
			"pt_br": "Aron: Hora do Holofote"
		},
		"date": 1759255200000,
		"dateEnd": 1759258800000,
		"pokemons": [
			{
				"speciesId": "aron",
				"kind": "5",
				"shiny": false
			}
		],
		"bonus": {
			"en": "2× Transfer Candy",
			"pt_br": "2× Doces ao transferir"
		},
		"imgUrl": "https://cdn.leekduck.com/assets/img/events/pokemonspotlighthour.jpg",
		"rawUrl": "https://leekduck.com/events/pokemonspotlighthour2025-09-30/"
	},
	{
		"title": {
			"en": "Ferroseed Spotlight Hour",
			"pt_br": "Ferroseed: Hora do Holofote"
		},
		"date": 1759860000000,
		"dateEnd": 1759863600000,
		"pokemons": [
			{
				"speciesId": "ferroseed",
				"kind": "5",
				"shiny": false
			}
		],
		"bonus": {
			"en": "2× Evolution XP",
			"pt_br": "2× XP ao evoluir"
		},
		"imgUrl": "https://cdn.leekduck.com/assets/img/events/pokemonspotlighthour.jpg",
		"rawUrl": "https://leekduck.com/events/pokemonspotlighthour2025-10-07/"
	},
	{
		"title": {
			"en": "Petilil Spotlight Hour",
			"pt_br": "Petilil: Hora do Holofote"
		},
		"date": 1760464800000,
		"dateEnd": 1760468400000,
		"pokemons": [
			{
				"speciesId": "petilil",
				"kind": "5",
				"shiny": false
			}
		],
		"bonus": {
			"en": "2× Catch Stardust",
			"pt_br": "2× Poeira Estelar ao capturar"
		},
		"imgUrl": "https://cdn.leekduck.com/assets/img/events/pokemonspotlighthour.jpg",
		"rawUrl": "https://leekduck.com/events/pokemonspotlighthour2025-10-14/"
	},
	{
		"title": {
			"en": "Gastly Spotlight Hour",
			"pt_br": "Gastly: Hora do Holofote"
		},
		"date": 1761069600000,
		"dateEnd": 1761073200000,
		"pokemons": [
			{
				"speciesId": "gastly",
				"kind": "5",
				"shiny": false
			}
		],
		"bonus": {
			"en": "2× Catch XP",
			"pt_br": "2× XP ao capturar"
		},
		"imgUrl": "https://cdn.leekduck.com/assets/img/events/pokemonspotlighthour.jpg",
		"rawUrl": "https://leekduck.com/events/pokemonspotlighthour2025-10-21/"
	},
	{
		"title": {
			"en": "Sinistea Spotlight Hour",
			"pt_br": "Sinistea: Hora do Holofote"
		},
		"date": 1761674400000,
		"dateEnd": 1761678000000,
		"pokemons": [
			{
				"speciesId": "sinistea",
				"kind": "5",
				"shiny": false
			}
		],
		"bonus": {
			"en": "2× Catch Candy",
			"pt_br": "2× Doces ao capturar"
		},
		"imgUrl": "https://cdn.leekduck.com/assets/img/events/pokemonspotlighthour.jpg",
		"rawUrl": "https://leekduck.com/events/pokemonspotlighthour2025-10-28/"
	}
]